wog_pkg/CurrencyRouletteGame.py
wog_pkg/Game.py
wog_pkg/GuessGame.py
wog_pkg/Live.py
wog_pkg/MainGame.py
wog_pkg/MemoryGame.py
wog_pkg/__init__.py
world_of_games_TomBrov-0.0.1.dist-info/LICENSE
world_of_games_TomBrov-0.0.1.dist-info/METADATA
world_of_games_TomBrov-0.0.1.dist-info/WHEEL
world_of_games_TomBrov-0.0.1.dist-info/top_level.txt
world_of_games_TomBrov-0.0.1.dist-info/RECORD
