Metadata-Version: 2.1
Name: world-of-games-TomBrov
Version: 0.0.1
Summary: Devops course project
Home-page: https://github.com/TomBrov/WorldOfGames
Author: TomBrov
Author-email: tbrovy@gmail.com
License: UNKNOWN
Platform: UNKNOWN
Classifier: Programming Language :: Python :: 3
Classifier: License :: OSI Approved :: MIT License
Classifier: Operating System :: OS Independent
Requires-Python: >=3.6
